structured_logger/__init__.py
structured_logger/_version.py
structured_logger/advanced.py
structured_logger/logger.py
structured_logger/py.typed
structured_logger/sentry_integration.py
structured_logger_railway-1.6.0.dist-info/WHEEL
structured_logger_railway-1.6.0.dist-info/METADATA
structured_logger_railway-1.6.0.dist-info/RECORD
