Metadata-Version: 2.3
Name: structured-logger-railway
Version: 1.6.0
Summary: A flexible structured JSON logger for Python applications
Keywords: logging,json,structured,railway,cloud,docker,kubernetes
Author: Nikita Yastreb, Patrick Ward
Author-email: Nikita Yastreb <yastrebnikita723@gmail.com>, Patrick Ward <pward17@gmail.com>
License: MIT
Classifier: Development Status :: 4 - Beta
Classifier: Intended Audience :: Developers
Classifier: License :: OSI Approved :: MIT License
Classifier: Operating System :: OS Independent
Classifier: Programming Language :: Python :: 3
Classifier: Programming Language :: Python :: 3.8
Classifier: Programming Language :: Python :: 3.9
Classifier: Programming Language :: Python :: 3.10
Classifier: Programming Language :: Python :: 3.11
Classifier: Programming Language :: Python :: 3.12
Classifier: Topic :: Software Development :: Libraries :: Python Modules
Classifier: Topic :: System :: Logging
Requires-Dist: sentry-sdk[fastapi]>=2.39.0
Requires-Python: >=3.8
Project-URL: Bug Tracker, https://github.com/zee229/structured-logger/issues
Project-URL: Documentation, https://github.com/zee229/structured-logger#readme
Project-URL: Homepage, https://github.com/zee229/structured-logger
Project-URL: Repository, https://github.com/zee229/structured-logger.git
